makeapi/__init__.py
makeapi-1.0.5.dist-info/LICENSE.txt
makeapi-1.0.5.dist-info/METADATA
makeapi-1.0.5.dist-info/WHEEL
makeapi-1.0.5.dist-info/top_level.txt
makeapi-1.0.5.dist-info/RECORD
