Metadata-Version: 2.1
Name: makeapi
Version: 1.0.5
Summary: A small pypi project, that allows you to make your own API.
Home-page: https://github.com/FrostiiWeeb/makeapi
Author: Alex Hutz
Author-email: frostiiweeb@gmail.com
License: MIT
Keywords: web
Platform: UNKNOWN
Classifier: Development Status :: 3 - Alpha
Classifier: Intended Audience :: Developers
Classifier: Topic :: Software Development :: Build Tools
Classifier: License :: OSI Approved :: MIT License
Classifier: Programming Language :: Python :: 3
Classifier: Programming Language :: Python :: 3.4
Classifier: Programming Language :: Python :: 3.5
Classifier: Programming Language :: Python :: 3.6
License-File: LICENSE.txt
